LICENSE
LICENSE.txt
MANIFEST.in
README.md
releash.py
setup.py
releash.egg-info/PKG-INFO
releash.egg-info/SOURCES.txt
releash.egg-info/dependency_links.txt
releash.egg-info/entry_points.txt
releash.egg-info/requires.txt
releash.egg-info/top_level.txt